{
  "name": "Dhaulagiri Trek",
  "slug": "dhaulagiri-trek",
  "location": "Baglung",
  "region": "Dhaulagiri Region",
  "country": "Nepal",
  "difficulty": "extreme",
  "duration_days": 18,
  "distance_km": 200,
  "max_altitude": 5500,
  "altitude_gain": 3000,
  "starting_point": "Beni",
  "ending_point": "Marpha",
  "daily_trek_hours": 7,
  "temperature_range": "-10 to 15°C",
  "permits_required": true,
  "guide_mandatory": true,
  "fitness_level_required": "high",
  "water_availability": true,
  "food_availability": true,
  "mobile_network_availability": false,
  "risk_level": "high",
  "altitude_sickness_risk": "high",
  "nearest_medical_facility_distance": 50,
  "evacuation_possible": true,
  "cost_min_usd": 2500,
  "cost_max_usd": 4500,
  "cultural_significance": "Sacred mountain to Hindu pilgrims",
  "group_size_min": 4,
  "group_size_max": 12,
  "popularity_score": 85,
  "is_active": true
}
